git_operations_tool/__init__.py
git_operations_tool/main.py
git_operations_tool/core/__init__.py
git_operations_tool/core/branches.py
git_operations_tool/core/operations.py
git_operations_tool/core/pull_requests.py
git_operations_tool/core/repository.py
git_operations_tool/core/utils.py
git_operations_tool/interface/__init__.py
git_operations_tool/interface/menu.py
git_operations_tool/interface/prompts.py
git_operations_tool-0.2.3.dist-info/licenses/LICENSE
tests/__init__.py
tests/test_basic.py
git_operations_tool-0.2.3.dist-info/METADATA
git_operations_tool-0.2.3.dist-info/WHEEL
git_operations_tool-0.2.3.dist-info/entry_points.txt
git_operations_tool-0.2.3.dist-info/top_level.txt
git_operations_tool-0.2.3.dist-info/RECORD
